ortho/__init__.py
ortho/__main__.py
ortho/__version__.py
ortho/_orthogonal_functions/__init__.py
ortho/_orthogonal_functions/declarations.py
ortho/_orthogonal_functions/display_utilities.py
ortho/_orthogonal_functions/orthogonal_functions.py
ortho/_orthogonal_functions/orthogonalization_utilities.py
ortho/_orthogonal_functions/plot_functions.py
ortho/_orthogonal_functions/plot_utilities.py
ortho/_parse_arguments/__init__.py
ortho/_parse_arguments/parse_arguments.py
ortho-0.4.1.dist-info/AUTHORS.txt
ortho-0.4.1.dist-info/LICENSE.txt
ortho-0.4.1.dist-info/METADATA
ortho-0.4.1.dist-info/WHEEL
ortho-0.4.1.dist-info/entry_points.txt
ortho-0.4.1.dist-info/top_level.txt
ortho-0.4.1.dist-info/RECORD
