Metadata-Version: 2.1
Name: ortho
Version: 0.4.1
Summary: Generate orthogonal set of functions
Home-page: https://github.com/ameli/ortho
Download-URL: https://github.com/ameli/ortho/archive/main.zip
Author: Siavash Ameli
Author-email: sameli@berkeley.edu
Project-URL: Documentation, https://github.com/ameli/ortho/blob/main/README.rst
Project-URL: Source, https://github.com/ameli/ortho
Project-URL: Tracker, https://github.com/ameli/ortho/issues
Keywords: orthogonal-functions regression sympy computer-algebragram-schmidt
Platform: Linux
Platform: OSX
Platform: Windows
Classifier: Programming Language :: Python :: 3.9
Classifier: Programming Language :: Python :: 3.10
Classifier: Programming Language :: Python :: 3.11
Classifier: Programming Language :: Python :: 3.12
Classifier: License :: OSI Approved :: BSD License
Classifier: Operating System :: OS Independent
Classifier: Natural Language :: English
Classifier: Intended Audience :: Science/Research
Classifier: Intended Audience :: Developers
Classifier: Topic :: Software Development
Classifier: Topic :: Software Development :: Libraries :: Python Modules
Requires-Python: >=3.9
License-File: LICENSE.txt
License-File: AUTHORS.txt
Requires-Dist: numpy
Requires-Dist: sympy
Requires-Dist: matplotlib
Provides-Extra: docs
Requires-Dist: sphinx ; extra == 'docs'
Requires-Dist: sphinx-math-dollar ; extra == 'docs'
Requires-Dist: sphinx-toggleprompt <0.4 ; extra == 'docs'
Requires-Dist: pydata-sphinx-theme ==0.9.0 ; extra == 'docs'
Requires-Dist: graphviz ; extra == 'docs'
Requires-Dist: sphinx-automodapi ; extra == 'docs'
Requires-Dist: numpydoc ; extra == 'docs'
Requires-Dist: sphinx-design ; extra == 'docs'
Requires-Dist: sphinx-prompt ; extra == 'docs'
Requires-Dist: sphinx-copybutton ; extra == 'docs'
Provides-Extra: test
Requires-Dist: pytest-cov ; extra == 'test'
Requires-Dist: codecov ; extra == 'test'
